baud generator /baud_rate_generator.v
`timescale 1ns/1ps
module baud_gen(clk, reset, q, tick);
   input wire clk, reset;
   output reg [11:0] q;   // 12-bit counter for counting up to 2604
   output reg tick;       // Tick should be a reg for controlled assertion
   parameter MAX_CNT = 2604;

   always @(posedge clk or posedge reset) begin
        if (reset) begin
            q <= 0;       // Reset counter
            tick <= 0;    // Ensure tick is also reset
        end
        else if (q == MAX_CNT) begin
            q <= 0;       // Reset counter after reaching maximum count
            tick <= 1;    // Assert tick for one clock cycle
        end
        else begin
            q <= q + 1;   // Increment counter
            tick <= 0;    // Ensure tick de-asserts immediately afterward
        end
   end
endmodule

rx added baud/rx.v
`define idle  3'b000
`define start 3'b001
`define trans 3'b010
`define stop  3'b011

module uart_rx(clk, reset, rxd, rx_done, data_out, tick);
    input clk, reset, rxd;
    output reg rx_done;
    output wire [7:0] data_out;
    output wire tick;  // Added tick as output declaration

    reg [2:0] ps, ns;
    reg [7:0] sbuf_reg, sbuf_next;
    reg [2:0] count_next, count_reg;

    reg [12:0] q;
    wire [12:0] q_next;

    // Memory block of state machine
    always @(posedge clk) begin
        if (reset) begin
            sbuf_reg <= 0;
            ps <= `idle;
            count_reg <= 0;
            rx_done <= 0;
        end else begin
            ps <= ns;
            count_reg <= count_next;
            sbuf_reg <= sbuf_next;
        end
    end

    // Next state logic and output block
    always @(*) begin
        ns = ps;
        sbuf_next = sbuf_reg;
        count_next = count_reg;

        case (ps)
            `idle: begin
                rx_done = 0;
                if (rxd == 0) ns = `start; // Detect start bit
            end

            `start: begin
                if (tick && rxd == 0) begin
                    ns = `trans;
                    count_next = 0;
                end
            end

            `trans: begin
                if (tick) begin
                    sbuf_next = {rxd, sbuf_next[7:1]};
                    if (count_reg == 7) ns = `stop;
                    else count_next = count_reg + 1;
                end
            end

            `stop: begin
                if (tick && rxd == 1) begin
                    ns = `idle;
                    rx_done = 1;
                end
            end

            default: ns = `idle;
        endcase
    end

    assign data_out = sbuf_reg;

    // Baud rate generator logic (adjusted for stable tick generation)
    always @(posedge clk or posedge reset) begin
        if (reset) q <= 0;
        else q <= q_next;
    end

    assign q_next = (q == 2604) ? 0 : q + 1; // Correct baud timing for 19200 baud rate
    assign tick = (q == 1302);                // Mid-bit sample tick signal
endmodule





//----------------------version 2-----------

// // `include "baud_rate_generator.v"

// `define idle 3'b000
// `define start 3'b001
// `define trans 3'b010
// `define stop 3'b011

// module uart_rx(clk, reset, rxd, rx_done, data_out);
//     input clk, reset, rxd;
//     output reg rx_done;
//     output wire [7:0] data_out;

//     reg [2:0] ps, ns;
//     reg [7:0] sbuf_reg, sbuf_next;
//     reg [2:0] count_next, count_reg;

//     reg [11:0] q;
//     wire [11:0] q_next;
//     wire tick;

//     // Declaring state machine

//     // Memory block of state machine
//     always @(posedge clk) begin
//         if (reset) begin
//             sbuf_reg <= 0;   // Resetting shift buffer
//             ps <= `idle;     // Initializing state to idle
//             count_reg <= 0;  // Resetting count
//             rx_done <= 0;    // Ensuring rx_done is cleared on reset
//         end else begin
//             ps <= ns;
//             count_reg <= count_next;
//             sbuf_reg <= sbuf_next;
//         end
//     end

//     // Next state block as well as output block of FSM
//     always @(*) begin
//         ns = ps;
//         sbuf_next = sbuf_reg;
//         count_next = count_reg;

//         // Declaring all the states now
//         case (ps)
//             `idle: begin
//                 $display($time, "----------IDLE STATE-----------");
//                 rx_done = 0; // Reset rx_done in idle state
//                 if (rxd == 0) begin
//                     ns = `start;
//                     $display($time, ">>>>>>>>>>>>>>IDLE STATE TO START STATE>>>>>>>>>>>>>>>>>>");
//                 end
//             end

//             `start: begin
//                 $display($time, "----------START STATE-----------");
//                 if (tick) begin
//                     ns = `trans;
//                     $display($time, ">>>>>>>>>>>>>> START STATE TO TRANS STATE >>>>>>>>>>>>>>>>>>");
//                     count_next = 0;
//                 end
//             end

//             `trans: begin
//                 $display($time, "---------- TRANS STATE-----------");
//                 if (tick) begin
//                     sbuf_next = {rxd, sbuf_next[7:1]}; // Stable shift with correct positioning
//                     if (count_reg == 7) begin
//                         ns = `stop;
//                         $display($time, ">>>>>>>>>>>>>> TRANS STATE to STOP STATE >>>>>>>>>>>>>>>>>>");
//                     end else begin
//                         count_next = count_reg + 1;
//                     end
//                 end
//             end

//             `stop: begin
//                 $display($time, "---------- STOP STATE-----------");
//                 if (tick) begin
//                     ns = `idle;
//                     $display($time, ">>>>>>>>>>>>>> STOP STATE to IDLE state >>>>>>>>>>>>>>>>>>");
//                     rx_done = 1;
//                 end
//             end

//             default: ns = `idle;
//         endcase
//     end

//     assign data_out = sbuf_reg; 

//     // Baud rate generator logic --------------------------
//     always @(posedge clk or posedge reset) begin
//         if (reset) begin
//             q <= 0;
//         end else begin
//             q <= q_next;
//         end
//     end

//     assign q_next = (q == 2604) ? 0 : q + 1;
//     assign tick = (q == 2604) ? 1 : 0; // Tick signal generation for baud rate timing

// endmodule



//--------------------- version 1 OG version----------------

// `define idle 3'b000
// `define start 3'b001
// `define trans 3'b010
// `define stop 3'b011

// module uart_rx(clk, reset, rxd,rx_done, data_out);
//     input clk, reset, rxd;
//     output reg rx_done;
//     output reg [7:0]data_out;

//     reg [2:0]ps, ns;
//     reg [7:0]sbuf_reg,sbuf_next;
//     reg [2:0] count_next, count_reg;

//     wire tick;

//     //declaring state machine

//     // memory block of state machine
//     always @(posedge clk) begin
//         if(reset) begin
//             sbuf_reg=0;
//             ps=`idle;
//             count_reg=0;
//         end
//         else begin
//             ps=ns;
//             count_reg=count_next;
//             sbuf_reg=sbuf_next;

//         end
//     end

//     // next state block as well as output block of FSM

//     always @(*) begin
//         ns=ps;
//         sbuf_next=sbuf_reg;
//         count_next=count_reg;

//         //declaring all the states now

//         case(ps)
//         `idle: begin
//             $display($time, "----------IDLE STATE-----------");
//             if(rxd==0) begin
//                 ns=`start;
//                 $display($time, ">>>>>>>>>>>>>>>>IDLE STATE TO START STATE>>>>>>>>>>>>>>>>>>");
//             end 
//         end

//         `start : begin
//            $display($time, "----------STARRT STATE-----------"); 
//            if(tick) begin
//             ns= `trans;
//             $display($time, ">>>>>>>>>>>>>>>> START STATE TO TRANS STATE >>>>>>>>>>>>>>>>>>");
//             count_next=0;

//            end
//         end

//         `trans: begin
//             $display($time, "---------- TRANS STATE-----------"); // here shifting takes place
//             if(tick) begin
//                 sbuf_next= {sbuf_next[7:1],rxd};// here we are concatening  this is shiftting
//                 if(count_reg==7) begin
//                     ns= `stop;
//                      $display($time, ">>>>>>>>>>>>>>>> TRANS STATE to STOP STATE >>>>>>>>>>>>>>>>>>");
//                 end
//                 else begin
//                     count_next= count_reg+1;
//                 end

//             end

            
//         end

//         `stop: begin
//             $display($time, "---------- STO PSTATE-----------"); 
//             if (tick) begin
//                 ns= `idle;
//                 $display($time, ">>>>>>>>>>>>>>>> STOP STATE to IDLE state >>>>>>>>>>>>>>>>>>");
//                 rx_done= 1;


                

//             end
//         end
//         default: ns=`idle;

//         endcase


        
//     end

//     assign data_out= sbuf_reg;




// endmodule

rx added baud/rx_tb.v
`include "rx.v"
`timescale 1ns/1ps

module test_rx;

    reg clk, reset, rxd;
    wire rx_done;
    wire [7:0] data_out;
    wire tick; // Corrected tick declaration as a wire

    uart_rx UUT(clk, reset, rxd, rx_done, data_out, tick); // Correct instantiation

    // 50 MHz clock
    always #10 clk = ~clk;

    initial begin
        clk = 0;
        rxd = 1; // UART idle state
        reset = 1; 
        #20 reset = 0; // Releasing reset

        #40 rxd = 0; // Start bit
        send_byte(8'hA5); // Send data 0xA5
        send_byte(8'h5A); // Send data 0x5A

        // Stop bit
        rxd = 1;  
        #26040; // Wait for completion
        $finish;
    end

    // Improved Data Task
    task send_byte(input [7:0] data);
    integer i;
    begin
        for (i = 0; i < 8; i = i + 1) begin
            @(posedge tick);  // Correct synchronization
            rxd = data[i];
        end
        @(posedge tick);  
        rxd = 1; // Stop bit
    end
    endtask

    initial begin
        $monitor("Time = %0t | RX_Done = %b | Data Out = %h", $time, rx_done, data_out);
        $dumpfile("receive.vcd");  
        $dumpvars(2, test_rx);
    end
endmodule








// `include "rx.v"
// `timescale 1ns/1ps

// module test_rx;

//     reg clk, reset, rxd;
//     wire rx_done;
//     wire [7:0] data_out;
//     wire tick;

//     uart_rx UUT(clk, reset, rxd, rx_done, data_out, tick); // insantiation of the moduel

//     always #10 clk= ~clk; // 50 mhz clock

//     initial begin
//         clk= 0;
//         reset=1; // here if will be exceuted
//         #11 reset =0; // here executing else .. we have taken #11 as it is bigger thatn 1/2 of time periond
//         #20 rxd=0; // marking the start b

//         $display($time, " ----start process-----");
        
//         rdata(1);
//         $display($time, " ----rdata 1-----");
//         rdata(0);
//         $display($time, " ----rdata 2-----");

//         rdata(1);
//         $display($time, " ----rdata 3-----");
//         rdata(0);
//         $display($time, " ----rdata 4-----");

//         rdata(1);
//         $display($time, " ----rdata 5-----");
//         rdata(0);
//         $display($time, " ----rdata 6-----");

//         rdata(1);
//         $display($time, " ----rdata 7-----");
//         rdata(0);
//         $display($time, " ----rdata 8-----"); 

//         // we need to supply stop bit after 8th bit
//         rdata(1);
//         $display($time, " ----stop bit-----"); 

//     end

//     task 
//        rdata: 
//         input inp;
//         begin
//             if (posedge tick) begin
//                 rxd= inp;
//                 $display($time, " ----supply data -----");
//             end

//         end
       
//     endtask

//     intial begin
//         $dumpfile("receiver.vcd");
//         $dumpvars(2, test_rx);
//     end


// endmodule

// module uart_rx_tb;

//     // Testbench signals
//     reg clk, reset, rxd;
//     wire rx_done;
//     wire [7:0] data_out;

//     // Instantiate the UART receiver
//     uart_rx uut (
//         .clk(clk),
//         .reset(reset),
//         .rxd(rxd),
//         .rx_done(rx_done),
//         .data_out(data_out)
//     );

//     // Clock generation (50 MHz)
//     always #10 clk = ~clk;  // 20ns period => 50 MHz

//     // Testbench tasks
//     task send_byte(input [7:0] data);
//         integer i;
//         begin
//             // Start bit
//             rxd = 0;
//             #8680; // One bit time (115200 baud rate)

//             // Data bits
//             for (i = 0; i < 8; i = i + 1) begin
//                 rxd = data[i];
//                 #8680;
//             end

//             // Stop bit
//             rxd = 1;
//             #8680;
//         end
//     endtask

//     // Test scenarios
//     initial begin
//         // VCD file for waveform analysis
//         $dumpfile("receive.vcd");
//         $dumpvars(0, uart_rx_tb);

//         // Initialize signals
//         clk = 0;
//         reset = 1;
//         rxd = 1; // Idle state for UART is high
//         #100;

//         // De-assert reset and begin testing
//         reset = 0;

//         // Send data bytes
//         send_byte(8'b10101010); // Alternating pattern
//         #100000; // Wait for some time

//         send_byte(8'b11001100); // Another data pattern
//         #100000; 

//         send_byte(8'b11110000); // Back-to-back data
//         #100000;

//         $display("Test Completed");
//         $finish;
//     end

//     // Monitor received data
//     always @(posedge rx_done) begin
//         $display("Received Data: %b", data_out);
//     end

// endmodule
 
 //------------------- version 1 OG module
// module test_rx;

//     reg clk, reset, rxd;
//     wire rx_done;
//     wire [7:0] data_out;
//     wire tick;

//     uart_rx UUT(clk, reset, rxd, rx_done, data_out, tick); // insantiation of the moduel

//     always #10 clk= ~clk; // 50 mhz clock

//     initial begin
//         clk= 0;
//         reset=1; // here if will be exceuted
//         #11 reset =0; // here executing else .. we have taken #11 as it is bigger thatn 1/2 of time periond
//         #20 rxd=0; // marking the start b

//         $display($time, " ----start process-----");
        
//         rdata(1);
//         $display($time, " ----rdata 1-----");
//         rdata(0);
//         $display($time, " ----rdata 2-----");

//         rdata(1);
//         $display($time, " ----rdata 3-----");
//         rdata(0);
//         $display($time, " ----rdata 4-----");

//         rdata(1);
//         $display($time, " ----rdata 5-----");
//         rdata(0);
//         $display($time, " ----rdata 6-----");

//         rdata(1);
//         $display($time, " ----rdata 7-----");
//         rdata(0);
//         $display($time, " ----rdata 8-----"); 

//         // we need to supply stop bit after 8th bit
//         rdata(1);
//         $display($time, " ----stop bit-----"); 

//     end

//     task 
//        rdata: 
//         input inp;
//         begin
//             if (posedge tick) begin
//                 rxd= inp;
//                 $display($time, " ----supply data -----");
//             end

//         end
       
//     endtask

//     intial begin
//         $dumpfile("receiver.vcd");
//         $dumpvars(2, test_rx);
//     end


// endmodule

rx added baud/receive.vcd
$date
	Sun Mar 16 03:51:12 2025
$end
$version
	Icarus Verilog
$end
$timescale
	1ps
$end
$scope module test_rx $end
$var wire 1 ! tick $end
$var wire 1 " rx_done $end
$var wire 8 # data_out [7:0] $end
$var reg 1 $ clk $end
$var reg 1 % reset $end
$var reg 1 & rxd $end
$scope module UUT $end
$var wire 1 $ clk $end
$var wire 8 ' data_out [7:0] $end
$var wire 1 % reset $end
$var wire 1 & rxd $end
$var wire 1 ! tick $end
$var wire 13 ( q_next [12:0] $end
$var reg 3 ) count_next [2:0] $end
$var reg 3 * count_reg [2:0] $end
$var reg 3 + ns [2:0] $end
$var reg 3 , ps [2:0] $end
$var reg 13 - q [12:0] $end
$var reg 1 " rx_done $end
$var reg 8 . sbuf_next [7:0] $end
$var reg 8 / sbuf_reg [7:0] $end
$upscope $end
$scope task send_byte $end
$var reg 8 0 data [7:0] $end
$var integer 32 1 i [31:0] $end
$upscope $end
$upscope $end
$enddefinitions $end
#0
$dumpvars
bx 1
bx 0
bx /
bx .
b0 -
bx ,
b0 +
bx *
bx )
b1 (
bx '
1&
1%
0$
bx #
x"
0!
$end
#10000
b0 )
b0 .
0"
b0 *
b0 ,
b0 #
b0 '
b0 /
1$
#20000
0$
0%
#30000
b10 (
b1 -
1$
#40000
0$
#50000
b11 (
b10 -
1$
#60000
b1 +
0$
b0 1
b10100101 0
0&
#70000
b100 (
b11 -
b1 ,
1$
#80000
0$
#90000
b101 (
b100 -
1$
#100000
0$
#110000
b110 (
b101 -
1$
#120000
0$
#130000
b111 (
b110 -
1$
#140000
0$
#150000
b1000 (
b111 -
1$
#160000
0$
#170000
b1001 (
b1000 -
1$
#180000
0$
#190000
b1010 (
b1001 -
1$
#200000
0$
#210000
b1011 (
b1010 -
1$
#220000
0$
#230000
b1100 (
b1011 -
1$
#240000
0$
#250000
b1101 (
b1100 -
1$
#260000
0$
#270000
b1110 (
b1101 -
1$
#280000
0$
#290000
b1111 (
b1110 -
1$
#300000
0$
#310000
b10000 (
b1111 -
1$
#320000
0$
#330000
b10001 (
b10000 -
1$
#340000
0$
#350000
b10010 (
b10001 -
1$
#360000
0$
#370000
b10011 (
b10010 -
1$
#380000
0$
#390000
b10100 (
b10011 -
1$
#400000
0$
#410000
b10101 (
b10100 -
1$
#420000
0$
#430000
b10110 (
b10101 -
1$
#440000
0$
#450000
b10111 (
b10110 -
1$
#460000
0$
#470000
b11000 (
b10111 -
1$
#480000
0$
#490000
b11001 (
b11000 -
1$
#500000
0$
#510000
b11010 (
b11001 -
1$
#520000
0$
#530000
b11011 (
b11010 -
1$
#540000
0$
#550000
b11100 (
b11011 -
1$
#560000
0$
#570000
b11101 (
b11100 -
1$
#580000
0$
#590000
b11110 (
b11101 -
1$
#600000
0$
#610000
b11111 (
b11110 -
1$
#620000
0$
#630000
b100000 (
b11111 -
1$
#640000
0$
#650000
b100001 (
b100000 -
1$
#660000
0$
#670000
b100010 (
b100001 -
1$
#680000
0$
#690000
b100011 (
b100010 -
1$
#700000
0$
#710000
b100100 (
b100011 -
1$
#720000
0$
#730000
b100101 (
b100100 -
1$
#740000
0$
#750000
b100110 (
b100101 -
1$
#760000
0$
#770000
b100111 (
b100110 -
1$
#780000
0$
#790000
b101000 (
b100111 -
1$
#800000
0$
#810000
b101001 (
b101000 -
1$
#820000
0$
#830000
b101010 (
b101001 -
1$
#840000
0$
#850000
b101011 (
b101010 -
1$
#860000
0$
#870000
b101100 (
b101011 -
1$
#880000
0$
#890000
b101101 (
b101100 -
1$
#900000
0$
#910000
b101110 (
b101101 -
1$
#920000
0$
#930000
b101111 (
b101110 -
1$
#940000
0$
#950000
b110000 (
b101111 -
1$
#960000
0$
#970000
b110001 (
b110000 -
1$
#980000
0$
#990000
b110010 (
b110001 -
1$
#1000000
0$
#1010000
b110011 (
b110010 -
1$
#1020000
0$
#1030000
b110100 (
b110011 -
1$
#1040000
0$
#1050000
b110101 (
b110100 -
1$
#1060000
0$
#1070000
b110110 (
b110101 -
1$
#1080000
0$
#1090000
b110111 (
b110110 -
1$
#1100000
0$
#1110000
b111000 (
b110111 -
1$
#1120000
0$
#1130000
b111001 (
b111000 -
1$
#1140000
0$
#1150000
b111010 (
b111001 -
1$
#1160000
0$
#1170000
b111011 (
b111010 -
1$
#1180000
0$
#1190000
b111100 (
b111011 -
1$
#1200000
0$
#1210000
b111101 (
b111100 -
1$
#1220000
0$
#1230000
b111110 (
b111101 -
1$
#1240000
0$
#1250000
b111111 (
b111110 -
1$
#1260000
0$
#1270000
b1000000 (
b111111 -
1$
#1280000
0$
#1290000
b1000001 (
b1000000 -
1$
#1300000
0$
#1310000
b1000010 (
b1000001 -
1$
#1320000
0$
#1330000
b1000011 (
b1000010 -
1$
#1340000
0$
#1350000
b1000100 (
b1000011 -
1$
#1360000
0$
#1370000
b1000101 (
b1000100 -
1$
#1380000
0$
#1390000
b1000110 (
b1000101 -
1$
#1400000
0$
#1410000
b1000111 (
b1000110 -
1$
#1420000
0$
#1430000
b1001000 (
b1000111 -
1$
#1440000
0$
#1450000
b1001001 (
b1001000 -
1$
#1460000
0$
#1470000
b1001010 (
b1001001 -
1$
#1480000
0$
#1490000
b1001011 (
b1001010 -
1$
#1500000
0$
#1510000
b1001100 (
b1001011 -
1$
#1520000
0$
#1530000
b1001101 (
b1001100 -
1$
#1540000
0$
#1550000
b1001110 (
b1001101 -
1$
#1560000
0$
#1570000
b1001111 (
b1001110 -
1$
#1580000
0$
#1590000
b1010000 (
b1001111 -
1$
#1600000
0$
#1610000
b1010001 (
b1010000 -
1$
#1620000
0$
#1630000
b1010010 (
b1010001 -
1$
#1640000
0$
#1650000
b1010011 (
b1010010 -
1$
#1660000
0$
#1670000
b1010100 (
b1010011 -
1$
#1680000
0$
#1690000
b1010101 (
b1010100 -
1$
#1700000
0$
#1710000
b1010110 (
b1010101 -
1$
#1720000
0$
#1730000
b1010111 (
b1010110 -
1$
#1740000
0$
#1750000
b1011000 (
b1010111 -
1$
#1760000
0$
#1770000
b1011001 (
b1011000 -
1$
#1780000
0$
#1790000
b1011010 (
b1011001 -
1$
#1800000
0$
#1810000
b1011011 (
b1011010 -
1$
#1820000
0$
#1830000
b1011100 (
b1011011 -
1$
#1840000
0$
#1850000
b1011101 (
b1011100 -
1$
#1860000
0$
#1870000
b1011110 (
b1011101 -
1$
#1880000
0$
#1890000
b1011111 (
b1011110 -
1$
#1900000
0$
#1910000
b1100000 (
b1011111 -
1$
#1920000
0$
#1930000
b1100001 (
b1100000 -
1$
#1940000
0$
#1950000
b1100010 (
b1100001 -
1$
#1960000
0$
#1970000
b1100011 (
b1100010 -
1$
#1980000
0$
#1990000
b1100100 (
b1100011 -
1$
#2000000
0$
#2010000
b1100101 (
b1100100 -
1$
#2020000
0$
#2030000
b1100110 (
b1100101 -
1$
#2040000
0$
#2050000
b1100111 (
b1100110 -
1$
#2060000
0$
#2070000
b1101000 (
b1100111 -
1$
#2080000
0$
#2090000
b1101001 (
b1101000 -
1$
#2100000
0$
#2110000
b1101010 (
b1101001 -
1$
#2120000
0$
#2130000
b1101011 (
b1101010 -
1$
#2140000
0$
#2150000
b1101100 (
b1101011 -
1$
#2160000
0$
#2170000
b1101101 (
b1101100 -
1$
#2180000
0$
#2190000
b1101110 (
b1101101 -
1$
#2200000
0$
#2210000
b1101111 (
b1101110 -
1$
#2220000
0$
#2230000
b1110000 (
b1101111 -
1$
#2240000
0$
#2250000
b1110001 (
b1110000 -
1$
#2260000
0$
#2270000
b1110010 (
b1110001 -
1$
#2280000
0$
#2290000
b1110011 (
b1110010 -
1$
#2300000
0$
#2310000
b1110100 (
b1110011 -
1$
#2320000
0$
#2330000
b1110101 (
b1110100 -
1$
#2340000
0$
#2350000
b1110110 (
b1110101 -
1$
#2360000
0$
#2370000
b1110111 (
b1110110 -
1$
#2380000
0$
#2390000
b1111000 (
b1110111 -
1$
#2400000
0$
#2410000
b1111001 (
b1111000 -
1$
#2420000
0$
#2430000
b1111010 (
b1111001 -
1$
#2440000
0$
#2450000
b1111011 (
b1111010 -
1$
#2460000
0$
#2470000
b1111100 (
b1111011 -
1$
#2480000
0$
#2490000
b1111101 (
b1111100 -
1$
#2500000
0$
#2510000
b1111110 (
b1111101 -
1$
#2520000
0$
#2530000
b1111111 (
b1111110 -
1$
#2540000
0$
#2550000
b10000000 (
b1111111 -
1$
#2560000
0$
#2570000
b10000001 (
b10000000 -
1$
#2580000
0$
#2590000
b10000010 (
b10000001 -
1$
#2600000
0$
#2610000
b10000011 (
b10000010 -
1$
#2620000
0$
#2630000
b10000100 (
b10000011 -
1$
#2640000
0$
#2650000
b10000101 (
b10000100 -
1$
#2660000
0$
#2670000
b10000110 (
b10000101 -
1$
#2680000
0$
#2690000
b10000111 (
b10000110 -
1$
#2700000
0$
#2710000
b10001000 (
b10000111 -
1$
#2720000
0$
#2730000
b10001001 (
b10001000 -
1$
#2740000
0$
#2750000
b10001010 (
b10001001 -
1$
#2760000
0$
#2770000
b10001011 (
b10001010 -
1$
#2780000
0$
#2790000
b10001100 (
b10001011 -
1$
#2800000
0$
#2810000
b10001101 (
b10001100 -
1$
#2820000
0$
#2830000
b10001110 (
b10001101 -
1$
#2840000
0$
#2850000
b10001111 (
b10001110 -
1$
#2860000
0$
#2870000
b10010000 (
b10001111 -
1$
#2880000
0$
#2890000
b10010001 (
b10010000 -
1$
#2900000
0$
#2910000
b10010010 (
b10010001 -
1$
#2920000
0$
#2930000
b10010011 (
b10010010 -
1$
#2940000
0$
#2950000
b10010100 (
b10010011 -
1$
#2960000
0$
#2970000
b10010101 (
b10010100 -
1$
#2980000
0$
#2990000
b10010110 (
b10010101 -
1$
#3000000
0$
#3010000
b10010111 (
b10010110 -
1$
#3020000
0$
#3030000
b10011000 (
b10010111 -
1$
#3040000
0$
#3050000
b10011001 (
b10011000 -
1$
#3060000
0$
#3070000
b10011010 (
b10011001 -
1$
#3080000
0$
#3090000
b10011011 (
b10011010 -
1$
#3100000
0$
#3110000
b10011100 (
b10011011 -
1$
#3120000
0$
#3130000
b10011101 (
b10011100 -
1$
#3140000
0$
#3150000
b10011110 (
b10011101 -
1$
#3160000
0$
#3170000
b10011111 (
b10011110 -
1$
#3180000
0$
#3190000
b10100000 (
b10011111 -
1$
#3200000
0$
#3210000
b10100001 (
b10100000 -
1$
#3220000
0$
#3230000
b10100010 (
b10100001 -
1$
#3240000
0$
#3250000
b10100011 (
b10100010 -
1$
#3260000
0$
#3270000
b10100100 (
b10100011 -
1$
#3280000
0$
#3290000
b10100101 (
b10100100 -
1$
#3300000
0$
#3310000
b10100110 (
b10100101 -
1$
#3320000
0$
#3330000
b10100111 (
b10100110 -
1$
#3340000
0$
#3350000
b10101000 (
b10100111 -
1$
#3360000
0$
#3370000
b10101001 (
b10101000 -
1$
#3380000
0$
#3390000
b10101010 (
b10101001 -
1$
#3400000
0$
#3410000
b10101011 (
b10101010 -
1$
#3420000
0$
#3430000
b10101100 (
b10101011 -
1$
#3440000
0$
#3450000
b10101101 (
b10101100 -
1$
#3460000
0$
#3470000
b10101110 (
b10101101 -
1$
#3480000
0$
#3490000
b10101111 (
b10101110 -
1$
#3500000
0$
#3510000
b10110000 (
b10101111 -
1$
#3520000
0$
#3530000
b10110001 (
b10110000 -
1$
#3540000
0$
#3550000
b10110010 (
b10110001 -
1$
#3560000
0$
#3570000
b10110011 (
b10110010 -
1$
#3580000
0$
#3590000
b10110100 (
b10110011 -
1$
#3600000
0$
#3610000
b10110101 (
b10110100 -
1$
#3620000
0$
#3630000
b10110110 (
b10110101 -
1$
#3640000
0$
#3650000
b10110111 (
b10110110 -
1$
#3660000
0$
#3670000
b10111000 (
b10110111 -
1$
#3680000
0$
#3690000
b10111001 (
b10111000 -
1$
#3700000
0$
#3710000
b10111010 (
b10111001 -
1$
#3720000
0$
#3730000
b10111011 (
b10111010 -
1$
#3740000
0$
#3750000
b10111100 (
b10111011 -
1$
#3760000
0$
#3770000
b10111101 (
b10111100 -
1$
#3780000
0$
#3790000
b10111110 (
b10111101 -
1$
#3800000
0$
#3810000
b10111111 (
b10111110 -
1$
#3820000
0$
#3830000
b11000000 (
b10111111 -
1$
#3840000
0$
#3850000
b11000001 (
b11000000 -
1$
#3860000
0$
#3870000
b11000010 (
b11000001 -
1$
#3880000
0$
#3890000
b11000011 (
b11000010 -
1$
#3900000
0$
#3910000
b11000100 (
b11000011 -
1$
#3920000
0$
#3930000
b11000101 (
b11000100 -
1$
#3940000
0$
#3950000
b11000110 (
b11000101 -
1$
#3960000
0$
#3970000
b11000111 (
b11000110 -
1$
#3980000
0$
#3990000
b11001000 (
b11000111 -
1$
#4000000
0$
#4010000
b11001001 (
b11001000 -
1$
#4020000
0$
#4030000
b11001010 (
b11001001 -
1$
#4040000
0$
#4050000
b11001011 (
b11001010 -
1$
#4060000
0$
#4070000
b11001100 (
b11001011 -
1$
#4080000
0$
#4090000
b11001101 (
b11001100 -
1$
#4100000
0$
#4110000
b11001110 (
b11001101 -
1$
#4120000
0$
#4130000
b11001111 (
b11001110 -
1$
#4140000
0$
#4150000
b11010000 (
b11001111 -
1$
#4160000
0$
#4170000
b11010001 (
b11010000 -
1$
#4180000
0$
#4190000
b11010010 (
b11010001 -
1$
#4200000
0$
#4210000
b11010011 (
b11010010 -
1$
#4220000
0$
#4230000
b11010100 (
b11010011 -
1$
#4240000
0$
#4250000
b11010101 (
b11010100 -
1$
#4260000
0$
#4270000
b11010110 (
b11010101 -
1$
#4280000
0$
#4290000
b11010111 (
b11010110 -
1$
#4300000
0$
#4310000
b11011000 (
b11010111 -
1$
#4320000
0$
#4330000
b11011001 (
b11011000 -
1$
#4340000
0$
#4350000
b11011010 (
b11011001 -
1$
#4360000
0$
#4370000
b11011011 (
b11011010 -
1$
#4380000
0$
#4390000
b11011100 (
b11011011 -
1$
#4400000
0$
#4410000
b11011101 (
b11011100 -
1$
#4420000
0$
#4430000
b11011110 (
b11011101 -
1$
#4440000
0$
#4450000
b11011111 (
b11011110 -
1$
#4460000
0$
#4470000
b11100000 (
b11011111 -
1$
#4480000
0$
#4490000
b11100001 (
b11100000 -
1$
#4500000
0$
#4510000
b11100010 (
b11100001 -
1$
#4520000
0$
#4530000
b11100011 (
b11100010 -
1$
#4540000
0$
#4550000
b11100100 (
b11100011 -
1$
#4560000
0$
#4570000
b11100101 (
b11100100 -
1$
#4580000
0$
#4590000
b11100110 (
b11100101 -
1$
#4600000
0$
#4610000
b11100111 (
b11100110 -
1$
#4620000
0$
#4630000
b11101000 (
b11100111 -
1$
#4640000
0$
#4650000
b11101001 (
b11101000 -
1$
#4660000
0$
#4670000
b11101010 (
b11101001 -
1$
#4680000
0$
#4690000
b11101011 (
b11101010 -
1$
#4700000
0$
#4710000
b11101100 (
b11101011 -
1$
#4720000
0$
#4730000
b11101101 (
b11101100 -
1$
#4740000
0$
#4750000
b11101110 (
b11101101 -
1$
#4760000
0$
#4770000
b11101111 (
b11101110 -
1$
#4780000
0$
#4790000
b11110000 (
b11101111 -
1$
#4800000
0$
#4810000
b11110001 (
b11110000 -
1$
#4820000
0$
#4830000
b11110010 (
b11110001 -
1$
#4840000
0$
#4850000
b11110011 (
b11110010 -
1$
#4860000
0$
#4870000
b11110100 (
b11110011 -
1$
#4880000
0$
#4890000
b11110101 (
b11110100 -
1$
#4900000
0$
#4910000
b11110110 (
b11110101 -
1$
#4920000
0$
#4930000
b11110111 (
b11110110 -
1$
#4940000
0$
#4950000
b11111000 (
b11110111 -
1$
#4960000
0$
#4970000
b11111001 (
b11111000 -
1$
#4980000
0$
#4990000
b11111010 (
b11111001 -
1$
#5000000
0$
#5010000
b11111011 (
b11111010 -
1$
#5020000
0$
#5030000
b11111100 (
b11111011 -
1$
#5040000
0$
#5050000
b11111101 (
b11111100 -
1$
#5060000
0$
#5070000
b11111110 (
b11111101 -
1$
#5080000
0$
#5090000
b11111111 (
b11111110 -
1$
#5100000
0$
#5110000
b100000000 (
b11111111 -
1$
#5120000
0$
#5130000
b100000001 (
b100000000 -
1$
#5140000
0$
#5150000
b100000010 (
b100000001 -
1$
#5160000
0$
#5170000
b100000011 (
b100000010 -
1$
#5180000
0$
#5190000
b100000100 (
b100000011 -
1$
#5200000
0$
#5210000
b100000101 (
b100000100 -
1$
#5220000
0$
#5230000
b100000110 (
b100000101 -
1$
#5240000
0$
#5250000
b100000111 (
b100000110 -
1$
#5260000
0$
#5270000
b100001000 (
b100000111 -
1$
#5280000
0$
#5290000
b100001001 (
b100001000 -
1$
#5300000
0$
#5310000
b100001010 (
b100001001 -
1$
#5320000
0$
#5330000
b100001011 (
b100001010 -
1$
#5340000
0$
#5350000
b100001100 (
b100001011 -
1$
#5360000
0$
#5370000
b100001101 (
b100001100 -
1$
#5380000
0$
#5390000
b100001110 (
b100001101 -
1$
#5400000
0$
#5410000
b100001111 (
b100001110 -
1$
#5420000
0$
#5430000
b100010000 (
b100001111 -
1$
#5440000
0$
#5450000
b100010001 (
b100010000 -
1$
#5460000
0$
#5470000
b100010010 (
b100010001 -
1$
#5480000
0$
#5490000
b100010011 (
b100010010 -
1$
#5500000
0$
#5510000
b100010100 (
b100010011 -
1$
#5520000
0$
#5530000
b100010101 (
b100010100 -
1$
#5540000
0$
#5550000
b100010110 (
b100010101 -
1$
#5560000
0$
#5570000
b100010111 (
b100010110 -
1$
#5580000
0$
#5590000
b100011000 (
b100010111 -
1$
#5600000
0$
#5610000
b100011001 (
b100011000 -
1$
#5620000
0$
#5630000
b100011010 (
b100011001 -
1$
#5640000
0$
#5650000
b100011011 (
b100011010 -
1$
#5660000
0$
